docxrev/__init__.py
docxrev/com.py
docxrev/docxrev.py
docxrev-0.2.4.dist-info/LICENSE
docxrev-0.2.4.dist-info/METADATA
docxrev-0.2.4.dist-info/WHEEL
docxrev-0.2.4.dist-info/top_level.txt
docxrev-0.2.4.dist-info/RECORD
