Metadata-Version: 2.1
Name: docxrev
Version: 0.2.4
Summary: Microsoft Word review tools (comments, markup, etc.) with Python
Home-page: https://github.com/blakeNaccarato/docxrev
Author: Blake Naccarato
Requires-Python: >=3.7
License-File: LICENSE
Requires-Dist: pywin32
Requires-Dist: fire
